aiidalab_qe_pp/__init__.py
aiidalab_qe_pp/__main__.py
aiidalab_qe_pp/aiida_critic2/calculations/__init__.py
aiidalab_qe_pp/aiida_critic2/parsers/__init__.py
aiidalab_qe_pp/app/__init__.py
aiidalab_qe_pp/app/code.py
aiidalab_qe_pp/app/model.py
aiidalab_qe_pp/app/result.py
aiidalab_qe_pp/app/setting.py
aiidalab_qe_pp/app/utils.py
aiidalab_qe_pp/app/widgets.py
aiidalab_qe_pp/app/workchain.py
aiidalab_qe_pp/app/result/__init__.py
aiidalab_qe_pp/app/result/model.py
aiidalab_qe_pp/app/result/result.py
aiidalab_qe_pp/app/result/widgets/cubevisualmodel.py
aiidalab_qe_pp/app/result/widgets/cubevisualwidget.py
aiidalab_qe_pp/app/result/widgets/ldos3dvisualmodel.py
aiidalab_qe_pp/app/result/widgets/ldos3dvisualwidget.py
aiidalab_qe_pp/app/result/widgets/stmvisualmodel.py
aiidalab_qe_pp/app/result/widgets/stmvisualwidget.py
aiidalab_qe_pp/app/result/widgets/wfnvisualmodel.py
aiidalab_qe_pp/app/result/widgets/wfnvisualwidget.py
aiidalab_qe_pp/workflows/ppworkchain.py
aiidalab_qe_pp-0.1.4.dist-info/entry_points.txt
aiidalab_qe_pp-0.1.4.dist-info/licenses/LICENSE
aiidalab_qe_pp-0.1.4.dist-info/WHEEL
aiidalab_qe_pp-0.1.4.dist-info/METADATA
aiidalab_qe_pp-0.1.4.dist-info/RECORD
