Metadata-Version: 2.4
Name: aiidalab-qe-pp
Version: 0.1.4
Summary: AiiDAlab quantum ESPRESSO app plugin for PP code
Author: Andres Ortega-Guerrero
Requires-Python: >=3.9
Classifier: Development Status :: 3 - Alpha
Classifier: Framework :: AiiDA
Classifier: License :: OSI Approved :: MIT License
Classifier: Operating System :: POSIX :: Linux
Classifier: Operating System :: MacOS :: MacOS X
Classifier: Programming Language :: Python :: 3
License-File: LICENSE
Requires-Dist: weas-widget==0.1.25
Requires-Dist: aiida-pythonjob==0.1.8
Requires-Dist: scikit-image
Requires-Dist: kaleido
Requires-Dist: ruff ; extra == "dev"
Project-URL: Homepage, https://github.com/AndresOrtegaGuerrero/aiidalab-qe-pp
Provides-Extra: dev
